{
  "project_info": {
    "project_number": "474708093013",
    "project_id": "login-df074",
    "storage_bucket": "login-df074.appspot.com"
  },
  "client": [
    {
      "client_info": {
        "mobilesdk_app_id": "1:474708093013:android:bb947ae7a29f23e04a8cdc",
        "android_client_info": {
          "package_name": "com.example.login_page"
        }
      },
      "oauth_client": [
        {
          "client_id": "474708093013-oul9794rekg1op89eg9gq64lsuqdflg8.apps.googleusercontent.com",
          "client_type": 3
        }
      ],
      "api_key": [
        {
          "current_key": "AIzaSyDLKJII7ZiY7e-EWxQpJWDdW4GnIBHSKf4"
        }
      ],
      "services": {
        "appinvite_service": {
          "other_platform_oauth_client": [
            {
              "client_id": "474708093013-oul9794rekg1op89eg9gq64lsuqdflg8.apps.googleusercontent.com",
              "client_type": 3
            }
          ]
        }
      }
    }
  ],
  "configuration_version": "1"
}